Metadata-Version: 2.1
Name: WordToPdf
Version: 0.1.1
Summary: Dynamsoft Barcode Reader Python project
Home-page: https://mail.163.com/js6/main.jsp?sid=PAlGWIYldfIQjfQTFYllFVEyKXidwtNk&df=mail163_letter#module=welcome.WelcomeModule%7C%7B%7D
Author: wangweidong
Author-email: 17891967090@163.com
License: Apache
Platform: UNKNOWN
Classifier: Programming Language :: Python
Requires-Python: >=3.8
